Workbook

Sheet Setup
A1: BUSINESS SETUP
A2: Enter your details — they appear across all sheets.
A4: Business Name:
A5: ABN:
A6: Builder Licence:
A7: Address:
A8: Phone:
A9: Email:
A11: PROJECT SETUP
A13: Project Name:
A14: Project Address:
A15: Client Name:
... A21: Valid Until:

Sheet Working Estimate
A1: WORKING ESTIMATE
A3: Item | B3: Description | C3: Qty | D3: Unit | E3: Rate ($) | F3: Cost ($) | G3: Margin % | H3: Quote Price ($)
A4: =IF(B4="","",ROW()-3) | F4: =IF(OR(C4="",E4=""),"",C4*E4) | H4: =IF(OR(F4="",G4=""),"",F4*(1+G4/100))
A5: =IF(B5="","",ROW()-3) | F5: =IF(OR(C5="",E5=""),"",C5*E5) | H5: =IF(OR(F5="",G5=""),"",F5*(1+G5/100))
A6: =IF(B6="","",ROW()-3) | F6: =IF(OR(C6="",E6=""),"",C6*E6) | H6: =IF(OR(F6="",G6=""),"",F6*(1+G6/100))
A7: =IF(B7="","",ROW()-3) | F7: =IF(OR(C7="",E7=""),"",C7*E7) | H7: =IF(OR(F7="",G7=""),"",F7*(1+G7/100))
A8: =IF(B8="","",ROW()-3) | F8: =IF(OR(C8="",E8=""),"",C8*E8) | H8: =IF(OR(F8="",G8=""),"",F8*(1+G8/100))
A9: =IF(B9="","",ROW()-3) | F9: =IF(OR(C9="",E9=""),"",C9*E9) | H9: =IF(OR(F9="",G9=""),"",F9*(1+G9/100))
A10: =IF(B10="","",ROW()-3) | F10: =IF(OR(C10="",E10=""),"",C10*E10) | H10: =IF(OR(F10="",G10=""),"",F10*(1+G10/100))
A11: =IF(B11="","",ROW()-3) | F11: =IF(OR(C11="",E11=""),"",C11*E11) | H11: =IF(OR(F11="",G11=""),"",F11*(1+G11/100))
A12: =IF(B12="","",ROW()-3) | F12: =IF(OR(C12="",E12=""),"",C12*E12) | H12: =IF(OR(F12="",G12=""),"",F12*(1+G12/100))
A13: =IF(B13="","",ROW()-3) | F13: =IF(OR(C13="",E13=""),"",C13*E13) | H13: =IF(OR(F13="",G13=""),"",F13*(1+G13/100))
A14: =IF(B14="","",ROW()-3) | F14: =IF(OR(C14="",E14=""),"",C14*E14) | H14: =IF(OR(F14="",G14=""),"",F14*(1+G14/100))
A15: =IF(B15="","",ROW()-3) | F15: =IF(OR(C15="",E15=""),"",C15*E15) | H15: =IF(OR(F15="",G15=""),"",F15*(1+G15/100))
... A33: =IF(B33="","",ROW()-3) | F33: =IF(OR(C33="",E33=""),"",C33*E33) | H33: =IF(OR(F33="",G33=""),"",F33*(1+G33/100))
E35: Subtotal: | F35: =SUM(F4:F34) -> 0 | H35: =SUM(H4:H34) -> 0
E36: GST (10%): | F36: =F35*0.1 -> 0 | H36: =H35*0.1 -> 0
E37: TOTAL: | F37: =F35+F36 -> 0 | H37: =H35+H36 -> 0

Sheet Quote Output
A1: =Setup!B4 -> 0
A2: =IF(Setup!B5="","","ABN: "&Setup!B5)
A4: QUOTATION
A6: Quote To: | B6: =Setup!B15 -> 0 | C6: =Setup!B19 -> 0
A7: Project: | B7: =Setup!B13 -> 0 | C7: =Setup!B20 -> 0
A9: Item | B9: Description | C9: Amount ($)
A10: =IF('Working Estimate'!B4="","",'Working Estimate'!A4) | B10: =IF('Working Estimate'!B4="","",'Working Estimate'!B4) | C10: =IF('Working Estimate'!H4="","",'Working Estimate'!H4)
A11: =IF('Working Estimate'!B5="","",'Working Estimate'!A5) | B11: =IF('Working Estimate'!B5="","",'Working Estimate'!B5) | C11: =IF('Working Estimate'!H5="","",'Working Estimate'!H5)
A12: =IF('Working Estimate'!B6="","",'Working Estimate'!A6) | B12: =IF('Working Estimate'!B6="","",'Working Estimate'!B6) | C12: =IF('Working Estimate'!H6="","",'Working Estimate'!H6)
A13: =IF('Working Estimate'!B7="","",'Working Estimate'!A7) | B13: =IF('Working Estimate'!B7="","",'Working Estimate'!B7) | C13: =IF('Working Estimate'!H7="","",'Working Estimate'!H7)
A14: =IF('Working Estimate'!B8="","",'Working Estimate'!A8) | B14: =IF('Working Estimate'!B8="","",'Working Estimate'!B8) | C14: =IF('Working Estimate'!H8="","",'Working Estimate'!H8)
A15: =IF('Working Estimate'!B9="","",'Working Estimate'!A9) | B15: =IF('Working Estimate'!B9="","",'Working Estimate'!B9) | C15: =IF('Working Estimate'!H9="","",'Working Estimate'!H9)
A16: =IF('Working Estimate'!B10="","",'Working Estimate'!A10) | B16: =IF('Working Estimate'!B10="","",'Working Estimate'!B10) | C16: =IF('Working Estimate'!H10="","",'Working Estimate'!H10)
A17: =IF('Working Estimate'!B11="","",'Working Estimate'!A11) | B17: =IF('Working Estimate'!B11="","",'Working Estimate'!B11) | C17: =IF('Working Estimate'!H11="","",'Working Estimate'!H11)
A18: =IF('Working Estimate'!B12="","",'Working Estimate'!A12) | B18: =IF('Working Estimate'!B12="","",'Working Estimate'!B12) | C18: =IF('Working Estimate'!H12="","",'Working Estimate'!H12)
A19: =IF('Working Estimate'!B13="","",'Working Estimate'!A13) | B19: =IF('Working Estimate'!B13="","",'Working Estimate'!B13) | C19: =IF('Working Estimate'!H13="","",'Working Estimate'!H13)
A20: =IF('Working Estimate'!B14="","",'Working Estimate'!A14) | B20: =IF('Working Estimate'!B14="","",'Working Estimate'!B14) | C20: =IF('Working Estimate'!H14="","",'Working Estimate'!H14)
A21: =IF('Working Estimate'!B15="","",'Working Estimate'!A15) | B21: =IF('Working Estimate'!B15="","",'Working Estimate'!B15) | C21: =IF('Working Estimate'!H15="","",'Working Estimate'!H15)
... A39: =IF('Working Estimate'!B33="","",'Working Estimate'!A33) | B39: =IF('Working Estimate'!B33="","",'Working Estimate'!B33) | C39: =IF('Working Estimate'!H33="","",'Working Estimate'!H33)
B41: Subtotal (excl. GST): | C41: ='Working Estimate'!H35 -> 0
B42: GST (10%): | C42: ='Working Estimate'!H36 -> 0
B43: TOTAL (incl. GST): | C43: ='Working Estimate'!H37 -> 0

Sheet Instructions
A1: HOW TO USE THIS ESTIMATE TO QUOTE CONVERTER
A3: QUICK START
A4: 1. Setup | B4: Enter business and project details.
A5: 2. Estimate | B5: Enter line items with costs.
A6: 3. Margin | B6: Set margin % per line to build markup.
A7: 4. Quote | B7: Quote Output sheet hides your margins.
