Workbook

Sheet Setup
A1: BUSINESS SETUP
A2: Enter your details - they will appear on the Summary dashboard.
A4: Business Name:
A5: ABN:
A6: Builder Licence:
A7: Address:
A8: Phone:
A9: Email:
A11: PROJECT SETUP
A13: Project Name:
A14: Project Address:
A15: Client Name:
... A19: Contract Date:
A20: Target Margin (%): | B20: 0.2

Sheet Variation Register
A1: VARIATION REGISTER
A2: Project: | B2: =Setup!B13 | E2: Client: | F2: =Setup!B15 | I2: Contract: | J2: =Setup!B16
A4: Var No. | B4: Date Raised | C4: Description | D4: Reason | E4: Status | F4: Quoted ($ ex GST) | G4: Actual ($ ex GST) | H4: Margin ($) | I4: Margin % | J4: Days | K4: Approved | L4: Invoice | M4: Invoiced | N4: Notes
A5: =IF(B5="","","VAR-"&TEXT(ROW()-4,"000")) | H5: =IF(OR(F5="",G5=""),"",F5-G5) | I5: =IF(OR(F5="",F5=0),"",H5/F5)
A6: =IF(B6="","","VAR-"&TEXT(ROW()-4,"000")) | H6: =IF(OR(F6="",G6=""),"",F6-G6) | I6: =IF(OR(F6="",F6=0),"",H6/F6)
A7: =IF(B7="","","VAR-"&TEXT(ROW()-4,"000")) | H7: =IF(OR(F7="",G7=""),"",F7-G7) | I7: =IF(OR(F7="",F7=0),"",H7/F7)
A8: =IF(B8="","","VAR-"&TEXT(ROW()-4,"000")) | H8: =IF(OR(F8="",G8=""),"",F8-G8) | I8: =IF(OR(F8="",F8=0),"",H8/F8)
A9: =IF(B9="","","VAR-"&TEXT(ROW()-4,"000")) | H9: =IF(OR(F9="",G9=""),"",F9-G9) | I9: =IF(OR(F9="",F9=0),"",H9/F9)
A10: =IF(B10="","","VAR-"&TEXT(ROW()-4,"000")) | H10: =IF(OR(F10="",G10=""),"",F10-G10) | I10: =IF(OR(F10="",F10=0),"",H10/F10)
A11: =IF(B11="","","VAR-"&TEXT(ROW()-4,"000")) | H11: =IF(OR(F11="",G11=""),"",F11-G11) | I11: =IF(OR(F11="",F11=0),"",H11/F11)
A12: =IF(B12="","","VAR-"&TEXT(ROW()-4,"000")) | H12: =IF(OR(F12="",G12=""),"",F12-G12) | I12: =IF(OR(F12="",F12=0),"",H12/F12)
A13: =IF(B13="","","VAR-"&TEXT(ROW()-4,"000")) | H13: =IF(OR(F13="",G13=""),"",F13-G13) | I13: =IF(OR(F13="",F13=0),"",H13/F13)
A14: =IF(B14="","","VAR-"&TEXT(ROW()-4,"000")) | H14: =IF(OR(F14="",G14=""),"",F14-G14) | I14: =IF(OR(F14="",F14=0),"",H14/F14)
A15: =IF(B15="","","VAR-"&TEXT(ROW()-4,"000")) | H15: =IF(OR(F15="",G15=""),"",F15-G15) | I15: =IF(OR(F15="",F15=0),"",H15/F15)
A16: =IF(B16="","","VAR-"&TEXT(ROW()-4,"000")) | H16: =IF(OR(F16="",G16=""),"",F16-G16) | I16: =IF(OR(F16="",F16=0),"",H16/F16)
... A54: =IF(B54="","","VAR-"&TEXT(ROW()-4,"000")) | H54: =IF(OR(F54="",G54=""),"",F54-G54) | I54: =IF(OR(F54="",F54=0),"",H54/F54)

Sheet Summary
A1: VARIATION SUMMARY DASHBOARD
A3: Project: | B3: =Setup!B13 | D3: Report Date: | E3: =TODAY()
A5: STATUS BREAKDOWN
A6: Requested | B6: =COUNTIF('Variation Register'!E:E,"Requested")
A7: Priced | B7: =COUNTIF('Variation Register'!E:E,"Priced")
A8: Approved | B8: =COUNTIF('Variation Register'!E:E,"Approved")
A9: Rejected | B9: =COUNTIF('Variation Register'!E:E,"Rejected")
A10: Invoiced | B10: =COUNTIF('Variation Register'!E:E,"Invoiced")
A11: Paid | B11: =COUNTIF('Variation Register'!E:E,"Paid")
A12: TOTAL VARIATIONS | B12: =COUNTA('Variation Register'!B5:B54)
A14: FINANCIAL SUMMARY
A15: Total Quoted (All) | B15: =SUM('Variation Register'!F:F)
A16: Total Quoted (Approved+) | B16: =SUMIF('Variation Register'!E:E,"Approved",'Variation Register'!F:F)+SUMIF('Variation Register'!E:E,"Invoiced",'Variation Register'!F:F)+SUMIF('Variation Register'!E:E,"Paid",'Variation Register'!F:F)
A17: Total Actual Cost | B17: =SUM('Variation Register'!G:G)
A18: Total Margin ($) | B18: =SUM('Variation Register'!H:H)
A19: Average Margin (%) | B19: =IFERROR(AVERAGE('Variation Register'!I:I),0)
A20: Total Days Impact | B20: =SUM('Variation Register'!J:J)
A22: CONTRACT IMPACT
A23: Original Contract Sum (ex GST) | B23: =Setup!B18
A24: Approved Variations | B24: =B16
A25: Revised Contract Sum (ex GST) | B25: =B23+B24
A26: Variation % of Contract | B26: =IFERROR(B24/B23,0)

Sheet Instructions
A1: HOW TO USE THIS VARIATION REGISTER
A3: QUICK START
A4: 1. Setup | B4: Enter your business and project details in the Setup sheet.
A5: 2. New Variation | B5: On the Register, enter the date in column B - this activates the row.
A6: 3. Details | B6: Fill in description, select reason and status from dropdowns.
A7: 4. Costs | B7: Enter Quoted amount (to client) and Actual cost (your cost).
A8: 5. Update | B8: Keep status current as variations progress through approval.
A9: 6. Review | B9: Check the Summary dashboard for totals and margin performance.
A11: STATUS WORKFLOW
A12: Requested | B12: Client has asked for a change
A13: Priced | B13: You have issued a Priced Variation Notice
A14: Approved | B14: Client has signed approval
A15: Rejected | B15: Client declined the variation
A16: Invoiced | B16: Included in a progress claim
A17: Paid | B17: Payment received
A19: CELL COLOURS
A20: Yellow | B20: Input cells - enter your data here
A21: Green | B21: Calculated fields - do not edit (formulas will break)
A23: TIPS
B24: - Margin calculates automatically from Quoted minus Actual
B25: - The Summary shows only Approved/Invoiced/Paid in contract totals
B26: - Back up this file regularly
